[
  {
    "message": "那天放学后直接去了东京。"
  },
  {
    "message": "这辆摩托车驶向东京的道路。"
  },
  {
    "message": "那家伙本来是要前往穆尔公募展的道路上的。"
  },
  {
    "message": "沿着那条路走去，在举行摩尔公募的场所附近的建筑物里进行了那件事。"
  },
  {
    "name": "直哉",
    "message": "“大盛況啊”"
  },
  {
    "message": "穆尔美术展的最后一天。\n展览会非常拥挤。"
  },
  {
    "name": "直哉",
    "message": "\"这就是所谓的莫尔美术展吧\""
  },
  {
    "names": [
      "坂本",
      "？？？"
    ],
    "message": "好久不见了呢。草薙Junior。"
  },
  {
    "message": "这个声音。"
  },
  {
    "name": "直哉",
    "message": "「好久不见了。坂本先生。」"
  },
  {
    "name": "坂本",
    "message": "“什么啊。光听声音就能明白了啊。”"
  },
  {
    "name": "直哉",
    "message": "坂本先生的说话方式很独特。"
  },
  {
    "name": "坂本",
    "message": "那是什么？你在嘲笑我吗？"
  },
  {
    "name": "直哉",
    "message": "“没有那样的事情”"
  },
  {
    "name": "坂本",
    "message": "“因为我们的基地在国外，大多数人甚至不知道我们回国了，你怎么知道的？” 转换为简体中文。"
  },
  {
    "name": "直哉",
    "message": "“是的。就算是像坂本彰三这样的人，参加摩尔奖获奖作品展也没问题吗？” \n\n"
  },
  {
    "name": "坂本",
    "message": "\"什么？\""
  },
  {
    "name": "直哉",
    "message": "「是名人吧」"
  },
  {
    "name": "坂本",
    "message": "“不知道怎么样。在这个场馆被要求签名只写了一次。” "
  },
  {
    "name": "直哉",
    "message": "这是真的吗？如果知道是坂本先生，签名会涌来的。"
  },
  {
    "name": "坂本",
    "message": "“啊，所以，只让年轻女孩写，结果只有一张。”"
  },
  {
    "name": "直哉",
    "message": "「啊，是吗。\r\n原来坂本先生也喜欢年轻的女孩子啊。」"
  },
  {
    "name": "坂本",
    "message": "「讨厌年轻女孩的男人应该不存在吧」"
  },
  {
    "name": "直哉",
    "message": "“不知道怎么样”"
  },
  {
    "name": "坂本",
    "message": "“什么？草薙Junior喜欢熟女吗？”"
  },
  {
    "name": "直哉",
    "message": "“怎么样呢。不知道。”"
  },
  {
    "name": "坂本",
    "message": "“什么啊。无聊的回答。那么，Junior在做什么？”"
  },
  {
    "name": "直哉",
    "message": "“不，我是来看画的。”"
  },
  {
    "name": "坂本",
    "message": "“我没听到这样的事情。\r\n现在Junior还在画画呢。”"
  },
  {
    "name": "直哉",
    "message": "是的，只是爱好程度而已。"
  },
  {
    "name": "坂本",
    "message": "“但是这不是其他职业吗？”"
  },
  {
    "name": "直哉",
    "message": "「我是一名美术老师」"
  },
  {
    "name": "坂本",
    "message": "\"老师啊。真无聊啊。\""
  },
  {
    "name": "直哉",
    "message": "“没有那样的事情。这是一份非常有趣的工作。”"
  },
  {
    "name": "坂本",
    "message": "“你别说那种话。你是在说你不来这边很无聊吧。教师这个职业很稳定，你来这边的可能性不大吧？”"
  },
  {
    "name": "直哉",
    "message": "“说出这样的话来的只有像坂本先生这样的人了”"
  },
  {
    "name": "坂本",
    "message": "\"那怎么样呢\""
  },
  {
    "name": "坂本",
    "message": "「我看到你在工作场所搞砸的那个家伙了」"
  },
  {
    "name": "直哉",
    "message": "「嗯？」"
  },
  {
    "name": "坂本",
    "message": "“有人说是布尔巴吉干的。这是光的作品。”"
  },
  {
    "name": "直哉",
    "message": "「啊啊，工作地点是弓张学园吗？\r\n是《樱花的色彩足迹》呢。」"
  },
  {
    "name": "坂本",
    "message": "“哎呀，好像是村田清彦在意的东西呢。”"
  },
  {
    "name": "直哉",
    "message": "这不是布尔巴基的作品吗？"
  },
  {
    "name": "坂本",
    "message": "「Junior……。你在小看我们吗？」"
  },
  {
    "name": "直哉",
    "message": "「啊，不……」"
  },
  {
    "message": "嗯，这些人不会被谎言所欺骗。"
  },
  {
    "name": "坂本",
    "message": "「村田也说了，那个，从设计上来看不是草薙健一郎吧。\r\n那是你的想法啊。」"
  },
  {
    "name": "坂本",
    "message": "「草薙健一郎如果考虑到那个问题，应该在生前已经公开发表了。」"
  },
  {
    "name": "直哉",
    "message": "为什么你会这么想呢？"
  },
  {
    "name": "坂本",
    "message": "“因为草薙健一郎在住院的医院屋顶上照射了光，对吧？按照这个逻辑，即使在住院期间也可以完全制作出来。”"
  },
  {
    "name": "坂本",
    "message": "实际的作品看起来像彩色玻璃，但可以用塑料纸代替。如果只是塑料纸的轮廓，自己制作几天就可以了。"
  },
  {
    "message": "完全正确。"
  },
  {
    "name": "直哉",
    "message": "\"无法匹敌呢\""
  },
  {
    "name": "直哉",
    "message": "「但是请保密这个事实」"
  },
  {
    "name": "坂本",
    "message": "“啊啊，嗯，有很多事情吧。像你们这样的公司职员”"
  },
  {
    "name": "直哉",
    "message": "“是的。私立学校的教师就像是公司职员一样。”"
  },
  {
    "name": "直哉",
    "message": "“话说回来，能够听到世界上的村田清彦这么说，真是光荣啊。”"
  },
  {
    "name": "坂本",
    "message": "“被埃兰·福克获奖作家关注，嗯，应该算是荣幸吧。”"
  },
  {
    "name": "直哉",
    "message": "“不过，在法国艺术杂志《Ecrits》上，被评选为全球最具影响力的100人-2001年版-之一的坂本先生夸奖我，这也是相当荣幸的。”"
  },
  {
    "name": "坂本",
    "message": "「啊，听到那个就啊。我觉得我的巅峰可能就在那附近吧。」"
  },
  {
    "name": "直哉",
    "message": "“你在说什么呢？今年一定要努力参加摩尔奖的申请啊。争取拿下世界啊。”"
  },
  {
    "name": "坂本",
    "message": "“是啊。今年要拿下来呢。”"
  },
  {
    "name": "坂本",
    "message": "“不过，年轻人也很努力啊。”"
  },
  {
    "name": "直哉",
    "message": "「在国内的话，可能并不是那么严重吧。」"
  },
  {
    "name": "坂本",
    "message": "“不不，其实也不是那样的。因为有些人一个人过得很好嘛。”"
  },
  {
    "name": "直哉",
    "message": "“真的吗？”"
  },
  {
    "name": "坂本",
    "message": "「啊啊，因为要继承自己的雅号，所以相当喜欢吧。」"
  },
  {
    "name": "直哉",
    "message": "\"宫崎三岁吗？\""
  },
  {
    "name": "坂本",
    "message": "「啊啊，就是那个」"
  },
  {
    "name": "直哉",
    "message": "确实出道比较晚，不过您会进入年轻人的行列吗？"
  },
  {
    "name": "坂本",
    "message": "「在我看来是年轻人啊」"
  },
  {
    "name": "坂本",
    "message": "哦，说到年轻人，长山香奈是吧。"
  },
  {
    "name": "直哉",
    "message": "是的"
  },
  {
    "name": "坂本",
    "message": "那个，他是你的熟人吗？"
  },
  {
    "name": "直哉",
    "message": "为什么？"
  },
  {
    "name": "坂本",
    "message": "\"如果问为什么，嗯，我不知道。\""
  },
  {
    "name": "坂本",
    "message": "「嗯嗯……」"
  },
  {
    "message": "坂本先生盯着我的脸看。"
  },
  {
    "name": "直哉",
    "message": "「什么，什么事？」"
  },
  {
    "name": "坂本",
    "message": "\"嗯\""
  },
  {
    "name": "坂本",
    "message": "「啊啊，大概明白了。原来如此啊。」"
  },
  {
    "name": "直哉",
    "message": "「什么事？」"
  },
  {
    "name": "坂本",
    "message": "嗯，草薙健一郎也受到女性的欢迎，大概就是那种感觉吧。"
  },
  {
    "name": "直哉",
    "message": "所以，是什么呢？"
  },
  {
    "name": "坂本",
    "message": "“那么，是什么呢。嗯，没关系啦。多亏了那个，我也能欣赏到那个光的作品了。”"
  },
  {
    "message": "那是什么？"
  },
  {
    "name": "坂本",
    "message": "“哦，这个时间了。差不多该去开会了。”"
  },
  {
    "name": "直哉",
    "message": "「这个时间开始开会真是辛苦啊」"
  },
  {
    "name": "坂本",
    "message": "“虽然说是商谈，但只是去喝酒而已。”"
  },
  {
    "name": "直哉",
    "message": "“免费的酒吗？”"
  },
  {
    "name": "坂本",
    "message": "那就是那样的事情了，草薙君。像我这样的名人，只会喝免费的酒。"
  },
  {
    "name": "直哉",
    "message": "\"羡慕\""
  },
  {
    "name": "坂本",
    "message": "那么，你也来这边吧。"
  },
  {
    "name": "直哉",
    "message": "“这可不是那么简单的事情。坂本先生最清楚不过了吧。”"
  },
  {
    "name": "坂本",
    "message": "所以你说什么呢？"
  },
  {
    "name": "直哉",
    "message": "\"确实\""
  },
  {
    "name": "坂本",
    "message": "\"那就这样吧，Junior。期待你的新作品哦。\""
  },
  {
    "name": "直哉",
    "message": "是的，谢谢。"
  },
  {
    "message": "坂本先生还是一如既往啊。"
  },
  {
    "message": "十年前的穆尔公募展以来，他是一个非常随和的人。"
  },
  {
    "name": "直哉",
    "message": "\"话说回来……\""
  },
  {
    "name": "直哉",
    "message": "「真厉害的人啊」"
  },
  {
    "message": "日本作品的人气非常惊人，但确实，草薙健一郎和御樱稟的人气更是突出。人群似乎非常拥挤。"
  },
  {
    "message": "看了真是不得了。"
  },
  {
    "name": "直哉",
    "message": "「那家伙的作品能看得懂吗？」"
  },
  {
    "message": "根据手册编号作为标志，步行到那个地方。"
  },
  {
    "message": "作品 No.30\n夏目圭作《向日葵》"
  },
  {
    "name": "直哉",
    "message": "“不会那么甜蜜吧。”"
  },
  {
    "message": "当然的事情当然是当然的。"
  },
  {
    "message": "虽然被御樱稟遮住了，但这家伙也是史上最年轻的大奖得主。"
  },
  {
    "message": "在颁发奖项之前，整个日本都在讨论稟的话题。"
  },
  {
    "message": "桂的画前也聚集了不亚于稟和父亲的人群。"
  },
  {
    "names": [
      "若者男A",
      "若者"
    ],
    "message": "「夭折的天才感觉啊。夏目圭啊。」"
  },
  {
    "names": [
      "若者男B",
      "若者"
    ],
    "message": "真的是天才啊。这是在十几岁的时候画的吧？太不可思议了吧。"
  },
  {
    "names": [
      "若者男A",
      "若者"
    ],
    "message": "“真遗憾啊。如果夏目圭还活着的话，他可能会成为御樱稟的竞争对手。”"
  },
  {
    "names": [
      "若者男B",
      "若者"
    ],
    "message": "“是啊。这家伙大概就是了。能够与御樱稟对抗的才能呢。”"
  },
  {
    "names": [
      "若者男A",
      "若者"
    ],
    "message": "\"相反地，我认为夏目圭比御樱稟更厉害。\""
  },
  {
    "names": [
      "若者男B",
      "若者"
    ],
    "message": "「有点明白了。御樱稟很厉害，但是夏目圭的《向日葵》有一种不是那种水平的厉害。有一种鬼气森森的感觉。」"
  },
  {
    "names": [
      "若者女A",
      "若者"
    ],
    "message": "你看过夏目圭的照片吗？"
  },
  {
    "names": [
      "若者女B",
      "若者"
    ],
    "message": "\"没有没有。什么样的？\""
  },
  {
    "names": [
      "若者女A",
      "若者"
    ],
    "message": "“像个女孩子一样可爱呢~”"
  },
  {
    "names": [
      "若者女B",
      "若者"
    ],
    "message": "“是啊。想看看。”"
  },
  {
    "names": [
      "若者女A",
      "若者"
    ],
    "message": "\"等一下，在网上……啊，找到了。找到了这张照片。\""
  },
  {
    "names": [
      "若者女B",
      "若者"
    ],
    "message": "“真的啊。好可爱啊。”"
  },
  {
    "names": [
      "若者女A",
      "若者"
    ],
    "message": "画了这么棒的画，还画得这么可爱。真的是失去了一个了不起的人呢。"
  },
  {
    "names": [
      "若者女B",
      "若者"
    ],
    "message": "如果还活着的话，一定会非常受欢迎的呢。"
  },
  {
    "message": "大概吧。\n如果是那个人物的话，大家都会喜欢他的。"
  },
  {
    "message": "但是，那个啊。年轻人们。\r\n因为在圭那里，“可爱”是禁句的。"
  },
  {
    "names": [
      "若者男A",
      "若者"
    ],
    "message": "今年日本人能否获奖呢？"
  },
  {
    "names": [
      "若者男B",
      "若者"
    ],
    "message": "“不知道呢。可能会很难吧。因为现在海外艺术家很受欢迎呢。”"
  },
  {
    "message": "嗯，毕竟已经有10年没得到了吧。谁会想今年能得到呢。"
  },
  {
    "names": [
      "若者男B",
      "若者"
    ],
    "message": "「布尔巴吉之类的很有趣啊」"
  },
  {
    "names": [
      "若者男A",
      "若者"
    ],
    "message": "那个人是个表演者吧。"
  },
  {
    "names": [
      "若者男B",
      "若者"
    ],
    "message": "我挺喜欢越野车的，不过其他人有没有人呢？"
  },
  {
    "names": [
      "若者男A",
      "若者"
    ],
    "message": "\"宫崎美子是谁？\""
  },
  {
    "names": [
      "若者男B",
      "若者"
    ],
    "message": "哦，没错，他在海外是相当受到高度评价的艺术家。"
  },
  {
    "names": [
      "若者男C",
      "若者"
    ],
    "message": "“不，不，他在国内也很有名。他被称为宫崎破戒的最后一名弟子，并且获得了小松良二奖的最高奖项。”"
  },
  {
    "names": [
      "若者男A",
      "若者"
    ],
    "message": "“但是啊，在卢·萨隆展上你不是输给了阿丽亚·何·墨水吗？”"
  },
  {
    "names": [
      "若者男C",
      "若者"
    ],
    "message": "「阿莉亚被誉为在下一个摩尔艺术节上获得最高奖项的艺术家。\r\n即使输了，宫崎骥子也获得了银奖。」"
  },
  {
    "names": [
      "若者男B",
      "若者"
    ],
    "message": "宫崎美子确实很厉害，但是公开发表的画作太少了。"
  },
  {
    "names": [
      "若者男C",
      "若者"
    ],
    "message": "“嗯，大概只能用一只手数过来吧。\r\n确实有点太少了……”"
  },
  {
    "names": [
      "若者男A",
      "若者"
    ],
    "message": "“虽然宫崎骏被称为了不起，但在国内几乎看不到他的作品。我从来没有看过他的作品，所以不太了解。”"
  },
  {
    "names": [
      "若者男C",
      "若者"
    ],
    "message": "“不，看了之后认识会改变的。”"
  },
  {
    "names": [
      "若者男B",
      "若者"
    ],
    "message": "“就算这么说，它在国内的展览中几乎没有出现过……”"
  },
  {
    "names": [
      "若者男C",
      "若者"
    ],
    "message": "“虽然是那样，但是……”"
  },
  {
    "names": [
      "若者男A",
      "若者"
    ],
    "message": "所以啊，还是夏目圭啊。"
  },
  {
    "names": [
      "若者男A",
      "若者"
    ],
    "message": "“即使宫崎美子说宫崎みすゞ有多厉害，她也只是个四十岁左右的人吧？”"
  },
  {
    "names": [
      "若者男A",
      "若者"
    ],
    "message": "对此，夏目圭在十几岁时创作了许多杰作，最终完成了这幅名画《向日葵》。"
  },
  {
    "names": [
      "若者男A",
      "若者"
    ],
    "message": "那个年纪就能画出这样的作品的天才，只有夏目圭这样的人。"
  },
  {
    "names": [
      "若者男C",
      "若者"
    ],
    "message": "如果那样说的话，御樱稟也是一样的。"
  },
  {
    "names": [
      "若者男B",
      "若者"
    ],
    "message": "“就算是这个意义，夏目圭在现在出名的人中是独一无二的。因为他可以被称为与那位御桜稟并列的艺术家。”"
  },
  {
    "names": [
      "若者男A",
      "若者"
    ],
    "message": "哦，真的是天壤之别啊。夏目圭这位画家。"
  },
  {
    "message": "电视和杂志等媒体上已经不怎么报道了，但艺术家夏目圭仍然受到了充分的爱戴。"
  },
  {
    "message": "当然，那只是他的才能而已。"
  },
  {
    "message": "实际上，听到这样的话真是令人高兴啊。"
  },
  {
    "message": "在人群中等待着能看到圭的画的时机，突然从后面有人喊了一声。"
  },
  {
    "names": [
      "桜子",
      "？？？"
    ],
    "message": "\"嗯？老师？\""
  },
  {
    "name": "直哉",
    "message": "\"嗯？\""
  },
  {
    "name": "直哉",
    "message": "咲崎君啊。你来了吗？"
  },
  {
    "name": "桜子",
    "message": "是的，今天是最后一天。"
  },
  {
    "name": "直哉",
    "message": "\"你一个人来的吗？\""
  },
  {
    "name": "奈津子",
    "message": "「我也是」"
  },
  {
    "name": "桜子",
    "message": "“从前就约好了，一起去的。”"
  },
  {
    "name": "直哉",
    "message": "“是啊，大家今天都很忙呢。”"
  },
  {
    "name": "桜子",
    "message": "“是的呢。我一直在练习说明会的演讲。我。”"
  },
  {
    "name": "直哉",
    "message": "看起来不错呢。辛苦了。"
  },
  {
    "name": "桜子",
    "message": "不，因为很开心，而且因为期待今天而努力了。"
  },
  {
    "name": "直哉",
    "message": "\"原来如此，展览会是奖励吗？\""
  },
  {
    "name": "桜子",
    "message": "是的"
  },
  {
    "name": "桜子",
    "message": "「第一次看到实物，非常、非常兴奋啊」"
  },
  {
    "name": "桜子",
    "message": "「我看了草薙健一郎的作品！太棒了！和在照片和电视上看到的完全不同。真是非常震撼！」"
  },
  {
    "name": "直哉",
    "message": "“是啊。实物看起来真的很棒。特别是树干的重量感，电视上绝对感受不到。”"
  },
  {
    "name": "桜子",
    "message": "是的，电视上看不懂。"
  },
  {
    "name": "桜子",
    "message": "顺便说一下，那个作品实际上是七部作品。包括《横卧的樱花》在内，是樱花七相图。老师知道吗？"
  },
  {
    "name": "直哉",
    "message": "「嗯？七部作……。\r\n啊，嗯，嗯，好像是这样的呢」"
  },
  {
    "name": "桜子",
    "message": "“在网上查找时写着这样的内容。但是，似乎无法看到剩下的六部作品的图片。好像是收藏它的人将其视为绝密。”"
  },
  {
    "name": "直哉",
    "message": "「那七部作中的六部作都已经进行了公开展示了呢。」"
  },
  {
    "name": "桜子",
    "message": "“但是，根据版权法非常严格，似乎在网上上传照片会很快被删除。”"
  },
  {
    "name": "直哉",
    "message": "哦，是这样啊。"
  },
  {
    "message": "嗯，理由可以想象。"
  },
  {
    "name": "桜子",
    "message": "那个，那个。御樱稟！那个人真的很厉害。"
  },
  {
    "name": "直哉",
    "message": "“啊，那个人已经超越了天才的范畴。\r\n草薙健一郎评价她是神灵附身的少女，也是唯一被认可的弟子。”"
  },
  {
    "name": "桜子",
    "message": "哎呀！您是御樱的门下生草薙健一郎的弟子吗？！"
  },
  {
    "name": "直哉",
    "message": "「虽然本人没有发言，但是穆尔基金会并没有否认这件事情。」"
  },
  {
    "name": "桜子",
    "message": "\"不、我不知道啊\""
  },
  {
    "name": "直哉",
    "message": "嗯，因为风格不太相似。但是很有名。\r\n由于穆拉没有正式说出来，两人的关系仍然被讨论着。"
  },
  {
    "name": "桜子",
    "message": "“学习不足了”"
  },
  {
    "name": "直哉",
    "message": "「准备室里有我买的美术杂志的往期，可以看看。里面有很多信息呢。」"
  },
  {
    "name": "直哉",
    "message": "刚才也听到了各种人的谈话声，但我很熟悉。\r\n大家都在读那种杂志做调查吧。"
  },
  {
    "name": "桜子",
    "message": "\"真厉害呢。老师周围真的都是厉害的人呢。\""
  },
  {
    "name": "直哉",
    "message": "「啊，是啊。御樱稟。草薙健一郎。还有夏目圭。\r\n他们都是超级天才。」"
  },
  {
    "name": "桜子",
    "message": "「我刚刚看了夏目圭先生的画呢。」"
  },
  {
    "name": "直哉",
    "message": "“怎么样？”"
  },
  {
    "name": "桜子",
    "message": "是的，简单来说非常棒。"
  },
  {
    "name": "直哉",
    "message": "\"大概吧\""
  },
  {
    "name": "桜子",
    "message": "“而且，我感受到了对草薙老师的注视。”"
  },
  {
    "name": "直哉",
    "message": "\"对我盯视？\""
  },
  {
    "name": "桜子",
    "message": "那朵向日葵有目光。"
  },
  {
    "name": "直哉",
    "message": "「视线吗……」"
  },
  {
    "name": "桜子",
    "message": "「老师是亲友，也是竞争对手。这句话很贴切。」"
  },
  {
    "name": "直哉",
    "message": "“那家伙比我有更多更多的才能。”"
  },
  {
    "name": "直哉",
    "message": "“然而，他把像我这样的家伙称为对手。”"
  },
  {
    "name": "桜子",
    "message": "“没有那样的事情。从那幅画中甚至可以感受到焦虑感。”"
  },
  {
    "name": "桜子",
    "message": "“或许，夏目圭先生在画那幅画的时候非常拼命。\r\n跑啊跑啊，一直奔跑着，追逐着什么东西。”"
  },
  {
    "name": "桜子",
    "message": "如果没有从老师那里听到夏目圭先生的事情，我想我就不知道在追求什么了。即便如此，我也能感受到他内心那股鬼气十足的冲动在推动着他。"
  },
  {
    "name": "桜子",
    "message": "夏目圭先生认真地追随老师，我认为。"
  },
  {
    "name": "直哉",
    "message": "“不知道怎么样”"
  },
  {
    "name": "直哉",
    "message": "“可能是那样，也可能不是那样。”"
  },
  {
    "name": "直哉",
    "message": "大概你最近才知道圭的事情吧？"
  },
  {
    "name": "桜子",
    "message": "“是的，最近才知道的。\r\n在听老师讲话之前，我甚至不知道他的名字。”"
  },
  {
    "name": "桜子",
    "message": "但是，我认为我仍然有这种感觉。"
  },
  {
    "name": "直哉",
    "message": "\"感受到了吗？\""
  },
  {
    "name": "桜子",
    "message": "「静静地站立着两朵向日葵。\r\n看起来仿佛在摇曳，但实际上却像是静止不动的一样。」"
  },
  {
    "name": "桜子",
    "message": "“看起来柔软，像铁一样锐利，像滴血一样，像冻结的瞬间一样……”"
  },
  {
    "name": "直哉",
    "message": "夏目圭作《向日葵》。\r\n以穆尔新人奖的待遇获奖的艾兰·奥塔利的作品。"
  },
  {
    "message": "确实是那样的作品。"
  },
  {
    "name": "桜子",
    "message": "「我对画并不懂，不太理解。但是，我感觉到圭先生的画作，像是在向某个人强烈地呼唤、诉求。」"
  },
  {
    "name": "桜子",
    "message": "那种感情非常复杂。虽然急切地追逐着，但也像是在欢闹，像是在生气，像是在悲伤，又像是在期待……"
  },
  {
    "name": "桜子",
    "message": "“我无法很好地解释，但是我有那种感觉。”"
  },
  {
    "message": "我不禁笑了起来。"
  },
  {
    "name": "桜子",
    "message": "哎呀，果然有点奇怪吗？"
  },
  {
    "name": "直哉",
    "message": "\"没关系，是正确的。真的讲得很清楚。\""
  },
  {
    "name": "直哉",
    "message": "呵呵呵，咲崎君的画或许还有待提高，但观察力却很出色啊。\r\n确实，他就是那样的人。"
  },
  {
    "name": "直哉",
    "message": "“总是兴奋、生气、悲伤着，一直在等待着我。”"
  },
  {
    "name": "直哉",
    "message": "确实，那幅画就是那样的画。"
  },
  {
    "message": "啊，对了。那是两朵向日葵的画。"
  },
  {
    "name": "直哉",
    "message": "「他也有很多作品吧？」"
  },
  {
    "name": "桜子",
    "message": "他也看了很多呢。宫崎破戒！"
  },
  {
    "name": "直哉",
    "message": "「啊啊，大御所啊」"
  },
  {
    "name": "桜子",
    "message": "「诺诺酱说她是粉丝，我也能理解。那个人太厉害了。」"
  },
  {
    "name": "直哉",
    "message": "“嗯，那个人是……”"
  },
  {
    "name": "直哉",
    "message": "\"嗯？\""
  },
  {
    "message": "在场内的杂乱中听不清楚，但感觉好像被叫了名字。"
  },
  {
    "name": "直哉",
    "message": "那是。"
  },
  {
    "name": "ルリヲ",
    "message": "「草薙小姐」"
  },
  {
    "name": "鈴菜",
    "message": "“想要思考的事情是一样的吧”"
  },
  {
    "name": "直哉",
    "message": "“你们也来了吗？”"
  },
  {
    "name": "鈴菜",
    "message": "“因为今天是新生欢迎会的最后一天，如果想去看的话，就只有今天这个时机了。”"
  },
  {
    "name": "ルリヲ",
    "message": "嗯，跟咲崎前辈比起来，要记住演讲什么的几乎是没有的。"
  },
  {
    "name": "鈴菜",
    "message": "“即使如此，失败也是不被允许的。”"
  },
  {
    "name": "直哉",
    "message": "\"原来如此\""
  },
  {
    "name": "ノノ未",
    "message": "嗯，想法是一样的呢。"
  },
  {
    "name": "直哉",
    "message": "“原来柊也来了吗！？”"
  },
  {
    "name": "ノノ未",
    "message": "“虽然我已经做了五次了。”"
  },
  {
    "name": "直哉",
    "message": "\"你已经来了五次了吗？真厉害啊\""
  },
  {
    "name": "ノノ未",
    "message": "是的，所以今天我也带了朋友来。"
  },
  {
    "name": "直哉",
    "message": "「朋友」"
  },
  {
    "name": "寧",
    "message": "抱歉。是我。"
  },
  {
    "name": "直哉",
    "message": "恩田也来了吗？"
  },
  {
    "name": "寧",
    "message": "是的，我是第三次了……"
  },
  {
    "name": "直哉",
    "message": "那还真是，恩田君也很热心呢。"
  },
  {
    "name": "ノノ未",
    "message": "“对了，如果宁酱也去得这么勤，我们就商量最后一天一起去吧。”"
  },
  {
    "name": "直哉",
    "message": "「柊君是美术迷，所以能理解，恩田君也是这样啊。」"
  },
  {
    "name": "寧",
    "message": "「有很多想要确认的事情……」"
  },
  {
    "name": "直哉",
    "message": "\"确认吗？\""
  },
  {
    "name": "寧",
    "message": "「啊，不，没什么的。」"
  },
  {
    "name": "ノノ未",
    "message": "那是那个意思吧。将来，想象着自己的画能够在这个展览会上展出。"
  },
  {
    "name": "寧",
    "message": "“我、我没有考虑那么夸张的事情啦。”"
  },
  {
    "name": "ルリヲ",
    "message": "“是这样吗。璐莉想了一下。”"
  },
  {
    "name": "ルリヲ",
    "message": "「展览会的画真是不错呢。毕竟看画才是最重要的啊。」"
  },
  {
    "name": "ルリヲ",
    "message": "「璐璃奥公开招募也是这样的事情啊。宁酱不一样吗？」"
  },
  {
    "name": "寧",
    "message": "“不知道怎么样呢。我可能有点不同。”"
  },
  {
    "name": "ルリヲ",
    "message": "「啊？不是吗？」"
  },
  {
    "name": "寧",
    "message": "「因为我有追逐自己的东西……」"
  },
  {
    "name": "ルリヲ",
    "message": "“原来如此，是探求性的东西呢。”"
  },
  {
    "name": "寧",
    "message": "“是”"
  },
  {
    "name": "鈴菜",
    "message": "「啊……」"
  },
  {
    "message": "场内的音乐变了。"
  },
  {
    "name": "桜子",
    "message": "「啊，音乐变了。这是？」"
  },
  {
    "name": "ルリヲ",
    "message": "\"回家的呼叫声呢\""
  },
  {
    "name": "ノノ未",
    "message": "“这是一首歌曲，叫做‘萤火虫之光’。”"
  },
  {
    "name": "鈴菜",
    "message": "这首曲子不是《萤火虫之光》，而是《别离的华尔兹》。\r\n虽然据说原本是同一首曲子。"
  },
  {
    "name": "寧",
    "message": "「我们差不多也该回去了吧」"
  },
  {
    "name": "ノノ未",
    "message": "那怎么样呢？"
  },
  {
    "name": "ノノ未",
    "message": "请看。人们正在不断地离开。"
  },
  {
    "name": "直哉",
    "message": "那当然啦。"
  },
  {
    "name": "ノノ未",
    "message": "「这个场馆总是人山人海，只能匆匆看一些画作。\r\n但是，当闭馆音乐响起时，即使是受欢迎的画作也会变得人烟稀少。」"
  },
  {
    "name": "寧",
    "message": "\"原来如此。如果最后只剩下一张，就可以慢慢地看了呢。\""
  },
  {
    "name": "ノノ未",
    "message": "“嘛，不止一张，可能会看到几张。”"
  },
  {
    "name": "直哉",
    "message": "“不可能一直待在这里吧。最后看一张大家都想看的画吧。”"
  },
  {
    "name": "桜子",
    "message": "“很好。最后再来一张。每个人都看自己想看的画，结束。”"
  },
  {
    "name": "直哉",
    "message": "“那样吧”"
  },
  {
    "message": "人气画作也逐渐变得稀少。"
  },
  {
    "message": "这样的话，就可以慢慢地看了。"
  },
  {
    "message": "每个人都聚集在他们“最后想看的画”前面。"
  },
  {
    "message": "本来应该的，但是。"
  },
  {
    "name": "直哉",
    "message": "难道不是每个人都要去看自己想看的画吗？"
  },
  {
    "name": "ノノ未",
    "message": "“这不就是答案吗？”"
  },
  {
    "name": "桜子",
    "message": "我当然是这幅画。"
  },
  {
    "name": "ルリヲ",
    "message": "“确实，这家伙内心涌动着各种情感呢。只看一眼的话太寂寞了吧。”"
  },
  {
    "name": "寧",
    "message": "夏目圭作《向日葵》"
  },
  {
    "message": "我们站在那幅画前面。"
  },
  {
    "message": "站在他画的画前面。"
  },
  {
    "message": "我感觉自己一直站在这幅画前面。"
  },
  {
    "message": "有点儿，这样站在这些人面前，感觉好像又可以继续走下去了。"
  },
  {
    "name": "直哉",
    "message": "“不，我从来没有停下来过。”"
  },
  {
    "name": "桜子",
    "message": "「是什么？」"
  },
  {
    "name": "直哉",
    "message": "不，这边的话。"
  },
  {
    "message": "是的。"
  },
  {
    "message": "这已经够长了。"
  },
  {
    "message": "然后，这将会是一个漫长的过程。"
  },
  {
    "name": "ルリヲ",
    "message": "大家一起牵手吧？"
  },
  {
    "name": "直哉",
    "message": "为什么？"
  },
  {
    "name": "ルリヲ",
    "message": "「不知道为什么」"
  },
  {
    "name": "鈴菜",
    "message": "「咕噜」"
  },
  {
    "message": "铃菜握住了我的手。"
  },
  {
    "name": "ルリヲ",
    "message": "「呃，好狡猾」"
  },
  {
    "name": "桜子",
    "message": "那么，老师的另一只手就是璐莉小姐的。"
  },
  {
    "name": "ルリヲ",
    "message": "可以吗？"
  },
  {
    "name": "桜子",
    "message": "「就地而言。比起那个，大家还是牵手吧。」"
  },
  {
    "message": "我们在圭的画前牵起了手。"
  },
  {
    "message": "原来如此，还有这样的走路方式呢。"
  },
  {
    "message": "我将与这些人，以及尚未见面的学生们一起，作为一名教师踏上征程。"
  },
  {
    "message": "校长的想法我稍微能理解。"
  },
  {
    "name": "桜子",
    "message": "「从现在开始加油吧」"
  },
  {
    "name": "奈津子",
    "message": "我们是最后一年了。"
  },
  {
    "name": "寧",
    "message": "「让我们做许多事情吧」"
  },
  {
    "name": "ルリヲ",
    "message": "「夏天去集训什么的真不错呢」"
  },
  {
    "name": "鈴菜",
    "message": "「鸟谷先生当部长的时候做得很好啊」"
  },
  {
    "name": "桜子",
    "message": "那么，那也做吧。"
  },
  {
    "name": "ノノ未",
    "message": "尽可能做到最好。"
  },
  {
    "name": "直哉",
    "message": "「太过丰富的话，我会很辛苦的……」"
  },
  {
    "name": "鈴菜",
    "message": "请加油哦。毕竟草薙先生是我们的老师呢……"
  },
  {
    "name": "直哉",
    "message": "\"你们的老师吗……\""
  },
  {
    "name": "鈴菜",
    "message": "\"那样吗？\""
  },
  {
    "message": "铃菜没有看着我，用小而有力的声音问道。"
  },
  {
    "message": "所以我回答了。"
  },
  {
    "name": "直哉",
    "message": "「啊啊，是啊……」"
  },
  {
    "name": "直哉",
    "message": "我是教师，而你们是重要的教子。"
  },
  {
    "name": "一同",
    "message": "「「「「「「是的」」」」」」"
  },
  {
    "message": "老师吗……。"
  },
  {
    "message": "不是作为艺术家，而是作为教师……。"
  },
  {
    "message": "我可以开始走不同的道路了吧。"
  },
  {
    "message": "「圭」- 玦"
  },
  {
    "message": "我会前往那里。"
  }
]